bposd/LICENSE
bposd/README.md
bposd/VERSION
bposd/__init__.py
bposd/css.py
bposd/css_decode_sim.py
bposd/hgp.py
bposd/stab.py
bposd-2.0.dist-info/LICENSE
bposd-2.0.dist-info/METADATA
bposd-2.0.dist-info/WHEEL
bposd-2.0.dist-info/top_level.txt
bposd-2.0.dist-info/RECORD
