Metadata-Version: 2.2
Name: bposd
Version: 2.0
Summary: BP+OSD
Home-page: https://roffe.eu/software/ldpc
Author: Joschka Roffe
Classifier: Intended Audience :: Science/Research
Requires-Python: >=3.9
License-File: LICENSE
Requires-Dist: ldpc>=2.0.0
Requires-Dist: numpy
Requires-Dist: scipy
Dynamic: author
Dynamic: classifier
Dynamic: description
Dynamic: description-content-type
Dynamic: home-page
Dynamic: requires-dist
Dynamic: requires-python
Dynamic: summary
